dicom_to_video/__about__.py
dicom_to_video/__init__.py
dicom_to_video/main.py
dicom_to_video-0.1.3.dist-info/METADATA
dicom_to_video-0.1.3.dist-info/WHEEL
dicom_to_video-0.1.3.dist-info/entry_points.txt
dicom_to_video-0.1.3.dist-info/licenses/LICENSE
dicom_to_video-0.1.3.dist-info/RECORD
