Metadata-Version: 2.4
Name: dicom-to-video
Version: 0.1.3
Summary: DICOM sequential medical images to AVI video
Project-URL: Homepage, https://github.com/jpchauvel/dicom-to-video
Project-URL: Documentation, https://github.com/jpchauvel/dicom-to-video/blob/main/README.md
Project-URL: Repository, https://github.com/jpchauvel/dicom-to-video
Project-URL: Issues, https://github.com/jpchauvel/dicom-to-video/issues
Author-email: Jean-Pierre Chauvel <jean.p.chauvel@gmail.com>
License: Creative Commons Legal Code
License-File: LICENSE
Classifier: Development Status :: 4 - Beta
Classifier: Intended Audience :: Developers
Classifier: Programming Language :: Python :: 3
Classifier: Programming Language :: Python :: 3.14
Classifier: Topic :: Software Development :: Build Tools
Requires-Python: <3.15,>=3.14
Requires-Dist: matplotlib>=3.10.7
Requires-Dist: opencv-python>=4.12.0.88
Requires-Dist: pydicom>=3.0.1
